{
    "AWSEBDockerrunVersion": 2,
    "containerDefinitions": [
        {
            "name": "client",
            "image": "sergerodriguezequisoft/multi-client",
            "hostname": "client",
            "essential": false
        },
        {
            "name": "server",
            "image": "sergerodriguezequisoft/multi-server",
            "hostname": "api",
            "essential": false
        },
        {
            "name": "worker",
            "image": "sergerodriguezequisoft/multi-worker",
            "hostname": "worker",
            "essential": false
        },
        {
            "name": "nginx",
            "image": "sergerodriguezequisoft/multi-nginx",
            "hostname": "nginx",
            "essential": true,
            "portMappings": [{
                "hostPort": 80,
                "containerPort": 80
            }],
            "links": ["client", "server"]

        }
    ]
}